odoo/addons/ssi_psychology/README.rst
odoo/addons/ssi_psychology/__init__.py
odoo/addons/ssi_psychology/__manifest__.py
odoo/addons/ssi_psychology/menu.xml
odoo/addons/ssi_psychology/demo/res_partner_demo.xml
odoo/addons/ssi_psychology/demo/res_users_demo.xml
odoo/addons/ssi_psychology/models/__init__.py
odoo/addons/ssi_psychology/models/res_company.py
odoo/addons/ssi_psychology/models/res_config_settings.py
odoo/addons/ssi_psychology/security/ir_module_category_data.xml
odoo/addons/ssi_psychology/security/res_group_data.xml
odoo/addons/ssi_psychology/static/description/icon.png
odoo/addons/ssi_psychology/static/img/albert-bandura.jpeg
odoo/addons/ssi_psychology/static/img/bf-skinner.jpeg
odoo/addons/ssi_psychology/static/img/carl-rogers.jpeg
odoo/addons/ssi_psychology/static/img/erik-erikson.jpeg
odoo/addons/ssi_psychology/static/img/ivan-pavlov.jpeg
odoo/addons/ssi_psychology/static/img/kurt-lewin.jpeg
odoo/addons/ssi_psychology/static/img/sigmund-freud.jpeg
odoo/addons/ssi_psychology/static/img/wilhelm-wundt.jpeg
odoo/addons/ssi_psychology/static/img/william-james.jpeg
odoo/addons/ssi_psychology/views/res_config_settings_views.xml
odoo14_addon_ssi_psychology-14.0.3.7.0.dist-info/METADATA
odoo14_addon_ssi_psychology-14.0.3.7.0.dist-info/WHEEL
odoo14_addon_ssi_psychology-14.0.3.7.0.dist-info/top_level.txt
odoo14_addon_ssi_psychology-14.0.3.7.0.dist-info/RECORD
